setup.py
DO_runin.egg-info/PKG-INFO
DO_runin.egg-info/SOURCES.txt
DO_runin.egg-info/dependency_links.txt
DO_runin.egg-info/entry_points.txt
DO_runin.egg-info/requires.txt
DO_runin.egg-info/top_level.txt
runin/DO.py
runin/__init__.py
runin/__main__.py
runin/runin.py